README.md
setup.py
ocean_model/Dynamic.py
ocean_model/Generalmodel.py
ocean_model/Model_1DV.py
ocean_model/__init__.py
ocean_model/test.py
ocean_model.egg-info/PKG-INFO
ocean_model.egg-info/SOURCES.txt
ocean_model.egg-info/dependency_links.txt
ocean_model.egg-info/not-zip-safe
ocean_model.egg-info/top_level.txt