Metadata-Version: 1.0
Name: ocean-model
Version: 0.1
Summary: python package to solve primitive equation of the ocean in one dimension
Home-page: UNKNOWN
Author: Jaouad Eddadsi
Author-email: jaouadeddadsi2016@gmail.com
License: UNKNOWN
Platform: UNKNOWN
